{
    "SongLyrics": [
      {
        "JpnStr": "間違[まちが]い探[さが]しの夜[よ]更[ふ]かし",
        "EngStr": "A night of searching for mistakes"
      },
      {
        "JpnStr": "あら楽[たの]しい",
        "EngStr": "Oh, how fun it is"
      },
      {
        "JpnStr": "迷[まよ]い子[こ]が手[て]招[まね]く夢[ゆめ]の国[くに]へ",
        "EngStr": "To the dreamland where the lost child beckons"
      },
      {
        "JpnStr": "アッチハソッチ?コッチハドッチ?",
        "EngStr": "Over here? Or over there?"
      },
      {
        "JpnStr": "電池[でんち]切[き]れ人生[じんせい]たちまち",
        "EngStr": "Life runs out in an instant"
      },
      {
        "JpnStr": "Let's パーティー",
        "EngStr": "Let's party"
      },
      {
        "JpnStr": "",
        "EngStr": ""
      },
      {
        "JpnStr": "博愛[はくあい]主義[しゅぎ]の皆々様[みなみなさま]ご立派[ごりっぱ]なことです",
        "EngStr": "Everyone with the philosophy of universal love, that is truly admirable"
      },
      {
        "JpnStr": "",
        "EngStr": ""
      },
      {
        "JpnStr": "ぐるぐるぐる踊[おど]りましょう",
        "EngStr": "Let's dance round and round"
      },
      {
        "JpnStr": "べたべたべた蔓延[はびこ]るの",
        "EngStr": "Stickiness is spreading"
      },
      {
        "JpnStr": "嘘[うそ]だらけ塗[ぬ]ったトースト",
        "EngStr": "Toast covered in lies"
      },
      {
        "JpnStr": "おひとついかが?",
        "EngStr": "Would you like one?"
      },
      {
        "JpnStr": "ワタシダケユウレイ",
        "EngStr": "Only I'm a ghost"
      },
      {
        "JpnStr": "",
        "EngStr": ""
      },
      {
        "JpnStr": "掻[か]き鳴[な]らした音[おと]は心地[ここち]悪[わる]いね",
        "EngStr": "The sound I strummed is unsettling"
      },
      {
        "JpnStr": "搾[しぼ]り出[だ]せ頭[あたま]の中[なか]ぜんぶ",
        "EngStr": "Squeeze out everything from inside my head"
      },
      {
        "JpnStr": "",
        "EngStr": ""
      },
      {
        "JpnStr": "完全[かんぜん]主義[しゅぎ]の皆々様[みなみなさま]右脳[うのう]が死[し]んでます?",
        "EngStr": "Everyone with the philosophy of perfectionism, has your right brain died?"
      },
      {
        "JpnStr": "",
        "EngStr": ""
      },
      {
        "JpnStr": "ゆらゆらゆら遊[あそ]びましょう",
        "EngStr": "Let's play swaying"
      },
      {
        "JpnStr": "どろどろどろ吐[は]き出[だ]すの",
        "EngStr": "Spitting out a mess"
      },
      {
        "JpnStr": "錆[さび]だらけ塗[ぬ]ったトースト",
        "EngStr": "Toast covered in rust"
      },
      {
        "JpnStr": "代[か]わりにいかが?",
        "EngStr": "Would you like a replacement?"
      },
      {
        "JpnStr": "ダレデスカユウレイ",
        "EngStr": "Who are you, a ghost?"
      },
      {
        "JpnStr": "",
        "EngStr": ""
      },
      {
        "JpnStr": "空[から]っぽの部屋[へや]で光[ひかり]は邪魔[じゃま]だね煙[けむり]の中[なか]でさえ",
        "EngStr": "In an empty room, even in the smoke, light is a nuisance"
      },
      {
        "JpnStr": "憂鬱[ゆううつ]は飲[の]み干[ほ]せ毒[どく]が抜[ぬ]けるまで",
        "EngStr": "Drink up the melancholy until the poison is drained"
      },
      {
        "JpnStr": "",
        "EngStr": ""
      },
      {
        "JpnStr": "後[うし]ろの正面[まえ]誰[だれ]?",
        "EngStr": "Who is in front of me?"
      },
      {
        "JpnStr": "わたしの顔[かお]が見[み]えた",
        "EngStr": "I saw my own face"
      },
      {
        "JpnStr": "",
        "EngStr": ""
      },
      {
        "JpnStr": "ぐるぐるぐる踊[おど]りましょう",
        "EngStr": "Let's dance round and round"
      },
      {
        "JpnStr": "べたべたべた蔓延[はびこ]るの",
        "EngStr": "Stickiness is spreading"
      },
      {
        "JpnStr": "嘘[うそ]だらけ塗[ぬ]ったトースト",
        "EngStr": "Toast covered in lies"
      },
      {
        "JpnStr": "一緒[いっしょ]にいかが?",
       

 "EngStr": "How about together?"
      },
      {
        "JpnStr": "",
        "EngStr": ""
      },
      {
        "JpnStr": "ぐちゃぐちゃぐちゃ笑[わら]いましょう",
        "EngStr": "Let's laugh all messy"
      },
      {
        "JpnStr": "ぞくぞくぞく歪[ゆが]めましょう",
        "EngStr": "Let's distort with thrill"
      },
      {
        "JpnStr": "錆[さび]だらけ塗[ぬ]ったトースト",
        "EngStr": "Toast covered in rust"
      },
      {
        "JpnStr": "もうひとついかが?",
        "EngStr": "Would you like one more?"
      },
      {
        "JpnStr": "ワタシダケユウレイ",
        "EngStr": "Only I'm a ghost"
      },
      {
        "JpnStr": "アナタモユウレイ",
        "EngStr": "Are you also a ghost?"
      }
    ],
    "ListVocab": [
      "間違い-まちがい",
      "探し-さがし",
      "夜更かし-よふかし",
      "あら-あら",
      "楽しい-たのしい",
      "迷い-まよい",
      "子-こ",
      "手招く-まねく",
      "夢-ゆめ",
      "国-くに",
      "アッチ-あっち",
      "ハソッチ-はそっち",
      "コッチ-こっち",
      "ハドッチ-はどっち",
      "電池-でんち",
      "切れ-きれ",
      "人生-じんせい",
      "たちまち-たちまち",
      "Let's-Let's",
      "パーティー-ぱーてぃー",
      "博愛-はくあい",
      "主義-しゅぎ",
      "の-の",
      "皆々様-みなみなさま",
      "ご立派-ごりっぱ",
      "な-な",
      "こと-こと",
      "ぐるぐる-ぐるぐる",
      "踊り-おどり",
      "べたべた-べたべた",
      "蔓延る-はびこる",
      "嘘-うそ",
      "だらけ-だらけ",
      "塗った-ぬった",
      "トースト-とーすと",
      "おひとつ-おひとつ",
      "いかが-いかが",
      "ワタシ-わたし",
      "ダケ-だけ",
      "ユウレイ-ゆうれい",
      "掻き鳴らし-かきならし",
      "音-おと",
      "心地悪い-ここちわるい",
      "ぜんぶ-ぜんぶ",
      "完全-かんぜん",
      "右脳-うのう",
      "死んで-しんで",
      "ます-ます",
      "ゆらゆら-ゆらゆら",
      "遊び-あそび",
      "どろどろ-どろどろ",
      "吐き出す-はきだす",
      "錆-さび",
      "代わり-かわり",
      "いかが-いかが",
      "アナタ-あなた",
      "モ-も",
      "空っぽ-からっぽ",
      "部屋-へや",
      "光-ひかり",
      "邪魔-じゃま",
      "ね-ね",
      "煙-けむり",
      "憂鬱-ゆううつ",
      "飲み干せ-のみほせ",
      "毒-どく",
      "抜ける-ぬける",
      "後ろ-うしろ",
      "正面-まえ",
      "誰-だれ",
      "わたし-わたし",
      "顔-かお",
      "見えた-みえた",
      "ぐちゃぐちゃ-ぐちゃぐちゃ",
      "笑い-わらい",
      "ぞくぞく-ぞくぞく",
      "歪め-ゆがめ",
      "もうひとつ-もうひとつ",
      "アナタ-あなた"
    ]
  }